setup.py
uasyncio.py
pycopy_cpython_uasyncio.egg-info/PKG-INFO
pycopy_cpython_uasyncio.egg-info/SOURCES.txt
pycopy_cpython_uasyncio.egg-info/dependency_links.txt
pycopy_cpython_uasyncio.egg-info/top_level.txt