Metadata-Version: 1.2
Name: pycopy-cpython-uasyncio
Version: 0.2.2
Summary: Pycopy module uasyncio ported to CPython
Home-page: https://github.com/pfalcon/pycopy-lib
Author: Paul Sokolovsky
Author-email: pycopy-dev@googlegroups.com
Maintainer: Paul Sokolovsky
Maintainer-email: pycopy-dev@googlegroups.com
License: Python
Platform: UNKNOWN
